{
    "language_iso_639_1": {
        "d2022_choose": "Rodný jazyk ?",
        "ar": "Arab",
        "bg": "bulharský",
        "bs": "Bosnian",
        "cs": "čeština",
        "da": "dánština",
        "de": "Němec",
        "el": "řecký",
        "en": "Angličtina",
        "es": "španělština",
        "et": "estonština",
        "fi": "Finský",
        "fr": "francouzština",
        "ga": "irština",
        "gd": "skotský",
        "he": "hebrejština",
        "hi": "hindština",
        "hr": "chorvatský",
        "hu": "maďarský",
        "is": "islandský",
        "it": "italština",
        "ja": "japonský",
        "lt": "Litevský",
        "lv": "lotyšský",
        "mg": "Malagasy",
        "nl": "holandský",
        "no": "Norwegian",
        "pl": "polština",
        "pt": "portugalština",
        "ro": "rumunština",
        "ru": "ruština",
        "sk": "Slovák",
        "sl": "slovinský",
        "sr": "srbština",
        "sv": "švédský",
        "uk": "ukrajinština",
        "zh": "čínština"
    },
    "home": {
        "findShareActivities": "Aktivity ke sdílení",
        "start": "Začít",
        "t2022_nativeLanguage": "Rodný jazyk",
        "t2022_selectLanguage": "Vyberte svůj jazyk",
        "info_line1": "aktivní členové, včetně",
        "info_line1Suite": "online",
        "info_line2": "Aktivity s",
        "info_line2Suite": "účastníci",
        "ConnectionIssues_jpi": "Ahoj, vaše připojení k internetu se zdá být vadné. Při vyřešení tohoto problému zkontrolujte nastavení a nabijte aplikaci."
    },
    "emailscreen": {
        "title": "Vítejte",
        "update_tittle_reset": "Obnovit heslo",
        "jpi_subtittle_1": "Vytvořte si účet nebo připojte:",
        "jpi_subtittle_reset": "Vyzkoušíme vaši paměť a nebojte se, pokud se mýlíte, obdržíte e -mail, abyste potvrdili, že jste vlastníkem svého účtu.",
        "label_1": "Zadejte svou e -mailovou adresu - povinné",
        "click_button_reset": "Bezpo to! Vložte svůj e-mail",
        "email": "E-mailem",
        "label_2": "Spojováním sebe přijímáte",
        "label_3": "Podmínky služby",
        "label_4": "a",
        "label_5": "Zásady ochrany osobních údajů",
        "button_1": "Následující",
        "label_7": "Zapomněli jste své heslo?",
        "button_3": "Obnovit heslo"
    },
    "passwordscreen": {
        "password": "Heslo",
        "label_2": "Spojováním sebe přijímáte",
        "label_3": "Podmínky použití",
        "label_4": "a",
        "label_5": "Zásady ochrany osobních údajů",
        "label_7": "Zapomněli jste své heslo?",
        "button_1": "Následující",
        "button_3": "Obnovit heslo"
    },
    "register": {
        "title": "Heslo",
        "password": "Heslo",
        "label_1": "Spojováním sebe přijímáte",
        "label_2": "Podmínky použití",
        "label_3": "a",
        "label_4": "Zásady ochrany osobních údajů",
        "button_1": "Následující",
        "label_6": "Zapomněli jste své heslo?",
        "label_7": "Obnovit heslo"
    },
    "verificationCode": {
        "title": "Ověření",
        "label_1": "Zadejte ověřovací kód přijatý e -mailem",
        "label_2": "Zadejte ověřovací kód",
        "button_1": "Šek",
        "label_3": "Nedostali jste ověřovací kód? (Zkontrolujte zpět svůj spam)",
        "button_2": "Zavrhnout",
        "subject": "Socializus - ověřovací kód -",
        "message": "Tuto zprávu jste obdrželi, protože jste se pokusili změnit heslo na socializus. Zadejte kód ###### do aplikace pro změnu hesla",
        "EmailConfirmation": "Ahoj! Pokud chcete v aplikaci vytvořit události, budete muset potvrdit svou e -mailovou adresu. Ale pokud dáváte přednost, můžete to udělat později.",
        "messageRoleChange": "Ahoj! Vložte tento kód ##### do aplikace a zkontrolujte e -mail",
        "t2022_reLoginMessage": "Váš e -mail je nyní zkontrolován! Znovu se připojte k aktualizaci svého účtu",
        "incorrectCode": "Nesprávný nebo vypršený kód",
        "emailError": "E -mail neexistuje"
    },
    "newPassword": {
        "title": "nové heslo",
        "label": "Zadejte své nové heslo",
        "password": "Heslo",
        "passConfirm": "Potvrďte heslo",
        "button": "Uložit heslo"
    },
    "createProfile": {
        "title": "Vytvořit profil",
        "button_1": "Pokračovat",
        "button_2": "Registrovat",
        "male": "mužský",
        "female": "Ženy",
        "perso": "Osobní účet",
        "pro": "Profesionální účet",
        "firstName": "Jméno",
        "BrandName": "Jméno značky",
        "lastName": "Příjmení",
        "ErrorFirstName": "Vaše křestní jméno nemůže obsahovat speciální znaky.",
        "ErrorlastName": "Vaše příjmení nemůže obsahovat speciální znaky.",
        "secretName": "Vaše příjmení je tajné, nebojte se 😉 Bude to užitečné pro další funkce.",
        "nickName": "Pseudo, značka nebo uživatelské jméno",
        "nickNametext": "Vaše přezdívka je jedinečná, takže nikdo jiný nemůže použít stejnou přezdívku. Pokud jste značka nebo bar, aktualizujte svou přezdívku hned teď!",
        "city": "Město",
        "nativeLanguage": "Rodný jazyk",
        "fakeUser": "Nechceme falešné uživatele. Přidejte do svého profilu fotografii a použijte tuto aplikaci.",
        "errorNickname": "Toto uživatelské jméno již přijalo jiný uživatel. Nabízíme toto uživatelské jméno, ale pokud si přejete, můžete jej změnit.",
        "imageSizeError": "Váš obrázek přesahuje maximální velikost. Nezapomeňte, že jsme neziskové sdružení, ale aplikaci rychle zlepšíme. Obráťte svůj obrázek pomocí našeho nástroje pro použití méně paměti."
    },
    "concept": [
        {
            "btnText": "Následující"
        },
        {
            "id": 1,
            "title": "Žádost o přátelské schůzky",
            "aboutDescription": "První žádost o přátelské schůzky, která pomáhá mezinárodním a organizátorům být a sdílet aktivity v jejich městě bydliště. Všechno bude brzy geolocováno a sdíleno s mobilními kartami a oznámeními, abyste na nic nezapomněli."
        },
        {
            "id": 2,
            "title": "Organizace nebo sdílení činností",
            "aboutDescription": "Večer doma, piknik, sportovní zasedání, kino, návštěva muzea, kulturní výlet, koncert, jídlo, ... Existuje mnoho témat, které lze vytvořit a sdílet vaše aktivity se socializusem. Brzy přicházejí nové funkce, které pozývají přátele, setkání a interakci s komentáři."
        },
        {
            "id": 3,
            "title": "Stýkat se s internacionály",
            "aboutDescription": "Seznamte se s novými přáteli, bavte se a promluvte si se všemi, všemi a ve všech jazycích je to vždy snazší s aplikací, která automaticky překládá vše. Jazyková bariéra již neexistuje, je čas se sdružovat, abyste si užili nezapomenutelný společenský život"
        }
    ],
    "menu": {
        "concept": "Pojem",
        "aboutUs": "O nás",
        "me": "Můj profil",
        "edit": "Upravit můj profil",
        "create": "Vytvořit událost",
        "past": "Minulé události",
        "invite": "Pozvat přátele",
        "vip": "VIP",
        "settings": "Nastavení",
        "news": "Zprávy",
        "contact": "Kontaktujte nás",
        "notifications": "Oznámení",
        "sponsorship": "Sponzorství",
        "update": "Aktualizace",
        "qrcode": "QR kód",
        "terms": "Podmínky použití",
        "logout": "Odhlásit se"
    },
    "updatescreen": {
        "text": "Nezapomeňte aktualizovat"
    },
    "modal_Image": {
        "modal_message": "Přidejte ke své činnosti ilustraci",
        "title_unsplash": "Hledání klíčových slov",
        "title_library": "Hledejte na svém zařízení",
        "find_message": "Hledejte obrázek pro aktivitu",
        "text_unsplash": "Najděte perfektní fotografii, která ilustruje vaši aktivitu a díky UNSplash přiláká více lidí.",
        "suggest_unsplash": "(Nebo se vraťte ke stažení vlastní fotografie)"
    },
    "bottomNav": {
        "activities": {
            "title": "Aktivity",
            "topNav": {
                "calendar": {
                    "title": "Kalendář"
                },
                "myActivities": {
                    "title": "Moje aktivity",
                    "topNav": {
                        "upcoming": "Nadcházející aktivity",
                        "past": "Minulé činnosti",
                        "liked": "Milované aktivity",
                        "organized": "Organizované aktivity"
                    }
                }
            }
        },
        "members": {
            "title": "Členové",
            "topNav": {
                "male": "-",
                "pro": "Profesionálové",
                "female": "-"
            },
            "notifications": {
                "title": "Oznámení"
            }
        },
        "maps": {
            "title": "Karty",
            "topNav": {
                "users": "Uživatelé",
                "activities": "Aktivity"
            }
        },
        "notifications": {
            "title": "Oznámení",
            "topNav": {
                "info": {
                    "title": "Informace"
                },
                "manage": {
                    "title": "Spravovat"
                },
                "interaction": {
                    "title": "Interakce"
                }
            }
        },
        "messages": {
            "title": "Zprávy"
        }
    },
    "contact": {
        "title": "Kontaktujte nás",
        "label_1": "V případě obtíží při připojení nás můžete kontaktovat prostřednictvím WhatsApp nebo telefonicky.",
        "label_2": "Různé skupiny WhatsApp jsou k dispozici podle vašich potřeb:",
        "picture": "Fotografie",
        "orga": "Organizace",
        "bug": "Chyba",
        "discord": "Svár",
        "telegram": "Telegram",
        "facebookGroup": "FB skupina",
        "label_3": "Telefonní číslo, které nás kontaktuje, je číslo příbytku:",
        "phone": "+33 8 99 49 01 44",
        "label_4": "Je to služba, která nám umožňuje přesměrování na všechny telefony lidí, kteří vám mohou pomoci mezi 10:00 a 18:00. Je to také způsob, jak poskytnout dar pro sdružení, protože se jedná o prémiové číslo.",
        "label_5": "Děkujeme vám za pochopení.",
        "label_6": "Tým Socializus",
        "button": "Registrovat"
    },
    "createActivity": {
        "title": "Vytvořte svou činnost",
        "title_mod": "Změna aktivity",
        "step1": {
            "create": "Vytvoří událost:",
            "activity": "Název aktivity",
            "address": "Adresa",
            "address_holder": "Nebo?",
            "chat": "Kočka",
            "online": "Online",
            "mapUrl": "Google Maps URL",
            "info": "Mapy Google Maps Adresa / URL",
            "dateTime": "Datum a hodina",
            "date": "datum",
            "start": "Začátek",
            "duration": "Doba trvání",
            "end": "KONEC",
            "unlimited": "Neomezené účastníci",
            "theOnly": "(Jediné bez omezení pro organizátory)",
            "attendee": "Omezení účastníků",
            "price": "Cena",
            "buyTicket": "Odkaz na nákup lístku",
            "howMuch": "Kolik přátel se mnou",
            "b2022_helpOrganizers": "Pomoc organizátorům",
            "b2022_reminderName": "Změňte název mého stažení",
            "b2022_coOrganizerRequest": "Požádejte o spoluorganizátory",
            "b2022_coOrganizerRequestChoice": "Vyberte požadavek na spoluorganizátor:",
            "b2022_coOrganizerMessage": "Obdržet soukromou zprávu",
            "b2022_coOrganizerRequestEarly": "Dorazí o 5 minut dříve k aktivitě",
            "b2022_coOrganizerMyOffer": "Chci nabídnout:",
            "b2022_coOrganizerOfferDrink": "Nápoj zdarma",
            "b2022_coOrganizerOfferPass": "Volný průsmyk",
            "b2022_coOrganizerOfferGift": "Jiný dárek",
            "b2022_coOrganizerGiftName": "Co nabídneš?",
            "continue": "Pokračovat"
        },
        "step2": {
            "choose": "Vyberte předmět:",
            "titleError": "Musíte zadat titul",
            "addressError": "Musíte zadat adresu nebo vybrat bod na kartě",
            "datetimeError": "Musíte vybrat datum a hodinu",
            "priceError": "Cenová hodnota není platná",
            "pricelinkError": "Odkaz na prodej vstupenek musí začít s 'http: //' nebo 'https: //'"
        },
        "step3": {
            "label": "Pokračujte ve vytváření aktivity:",
            "inOrder": "Chcete -li zvýšit zájem o své činnosti, doporučujeme vám přizpůsobit svou událost s obrazem pokrytí, ale v případě, že jej potřebujete, obdržíte automatickou ilustraci podle vašeho předmětu.",
            "please": "Prosím, vysvětlete svou činnost trochu více:",
            "addPhoto": "Přidejte obrázky",
            "addMore": "Přidej víc",
            "description": "Popis",
            "how": "Jak mě najít",
            "goBack": "Předchozí",
            "continue": "Pokračovat",
            "publish": "Publikovat",
            "topicError": "Musíte vybrat předmět"
        },
        "step4": {
            "allow": "Umožněte lidem stát se spoluorganizátorem",
            "manage": "Spravujte omezení",
            "select": "Vyberte lidi",
            "other": "Jiné sociální sítě",
            "whatsapp": "WhatsApp Group Link",
            "fbGroup": "Facebook Group",
            "fbPage": "facebooková stránka",
            "meetup": "Setkání",
            "telegram": "Telegram",
            "link": "Další odkaz",
            "b2022_optionalFeatures": "Volitelné funkce pro vaši činnost:",
            "b2022_friendsOnly": "Viditelná událost pouze pro přátele",
            "b2022_phoneNumberVisible": "Telefonní číslo viditelné pouze pro účastníky",
            "b2022_repeatEvent": "Opakujte událost",
            "b2022_weekly": "Týdně",
            "b2022_monthly": "Měsíční",
            "b2022_yearly": "Roční",
            "b2022_selectDays": "Vyberte dny:",
            "b2022_monday": "pondělí",
            "b2022_tuesday": "úterý",
            "b2022_wednesday": "středa",
            "b2022_thursday": "ČTVRTEK",
            "b2022_friday": "pátek",
            "b2022_saturday": "SOBOTA",
            "b2022_sunday": "Neděle",
            "b2022_parity": "Spravovat paritu",
            "b2022_allowGuests": "Autorizovat hosty",
            "b2022_ageRestrict": "Věkové omezení",
            "b2022_infoLine": "Informační linie",
            "publish": "Publikovat",
            "imageError": "Musíte vybrat obrázek",
            "descriptionError": "Musíte napsat popis",
            "howToFindError": "Musíte vysvětlit, jak se ocitnout"
        }
    },
    "editProfile": {
        "title": "Změňte svůj profil",
        "step1": {
            "personal": "Osobní účet",
            "pro": "Profesionální účet",
            "firstName": "Jméno",
            "nickname": "Pseudo, značka nebo uživatelské jméno",
            "title_city": "Aktivity kolem vašeho města",
            "city": "Město",
            "title_language": "Viditelné na vašem profilu",
            "nativeLanguage": "Rodný jazyk",
            "app_language": "Aplikační jazyk",
            "app_display": "Zobrazení aplikace"
        },
        "errMess": {
            "t2022_ErrFirstName": "Chybějící křestní jméno",
            "t2022_ErrNameAnomaly": "První jméno nemůže obsahovat postavy nebo speciální znaky",
            "t2022_ErrNickname": "Chybějící pseudo",
            "t2022_ErrNickAnomaly": "Pseudo max 15 písmen",
            "t2022_ErrNickAnomaly2": "Přezdívka již existuje",
            "t2022_ErrNickAnomaly3": "Přezdívka nemůže obsahovat speciální znaky",
            "t2022_ErrCity": "Chybějící město",
            "t2022_ErrCityAnomaly": "Městské pole nemůže obsahovat postavy nebo speciální postavy",
            "t2022_ErrLastName": "Chybějící příjmení",
            "t2022_ErrLastNameAnomaly": "Příjmení nemůže obsahovat postavy nebo speciální znaky",
            "t2022_ErrPhone": "Vložte prosím platné číslo",
            "t2022_ErrBirth": "JJ/MM/AAAA",
            "t2022_ErrBirth2": "Musíte být věkem",
            "t2022_ErrMail": "Chybějící e -mail",
            "t2022_ErrMail2": "Vložte prosím platný e-mail"
        },
        "step2": {
            "secret": "TAJNÝ",
            "info": "Informace",
            "warning": "Chcete -li přidat přátele, vytvářet události a odesílat soukromé zprávy, musíte zde nechat informace",
            "membership": "Vaše číslo člena je:",
            "title_lastname": "Příjmení je zbaveno pro každého",
            "lastName": "Příjmení",
            "noWorries": "(Nebojte se, je to tajemství)",
            "title_phone": "Telefonní číslo je pro organizátory povinné",
            "phone": "Telefonní číslo",
            "title_birthday": "Dobrý důvod k organizaci!",
            "birthday": "Datum narození",
            "title_mail": "Snadný způsob, jak vás přidat jako Ani",
            "email": "Emailová adresa",
            "message_chat": "Aplikace ještě neskončila, ale brzy si můžete povídat soukromě se svými skutečnými přáteli ...",
            "label": "Lidé vás mohou přidat jako IMO, aby vám poslali soukromé zprávy, pokud znají vaše:",
            "number": "Číslo člena",
            "private": "Je to soukromé pro každého",
            "save": "Zajistit",
            "continue": "Pokračovat",
            "previous": "Předchozí",
            "next": "Následující"
        },
        "step3": {
            "public_informations": "Veřejná informace",
            "more": "Více o vás",
            "about": "O tobě",
            "example": "Ahoj. Jmenuji se ... chci potkat nové lidi ...",
            "what": "Co rád dělám:",
            "spoken": "Mluvené jazyky:",
            "children": "Děti",
            "tobacco": "Tabák",
            "alcohol": "Alkohol",
            "yes": "Ano",
            "no": "Ne",
            "secret": "tajný",
            "sometimes": "Někdy",
            "submit": "Předložit"
        }
    },
    "profile": {
        "title": "Profil",
        "years": "Roky",
        "points": "body",
        "addFriend": "Přidat jako přítele",
        "chat": "Kočka",
        "block": "Zablokovat",
        "info": "Informace",
        "activities": "Aktivity",
        "network": "Síť",
        "friends": "Přátelé",
        "attending": "Přítomnost",
        "reliability": "Spolehlivost",
        "missing": "Chybějící",
        "lastConnection": "poslední připojení",
        "rating": "Organizátor",
        "registration": "Datum registrace",
        "about": "O mně",
        "native": "Rodný jazyk",
        "spoken": "Mluvené jazyky",
        "city": "Město",
        "children": "Děti",
        "tobacco": "Tabák",
        "alcohol": "Alkohol",
        "done": "Prováděné aktivity",
        "what": "Co rád dělám",
        "evaluations": "Hodnocení",
        "afterwork": "Po práci:",
        "culture": "Kultura:",
        "job": "Práce:",
        "mutual": "Vzájemná pomoc:",
        "picnic": "Piknik:",
        "aperitif": "Aperitiv:",
        "game": "Hry:",
        "linguistic": "Lingvistické:",
        "music": "Hudba:",
        "sports": "Sportovní:",
        "cinema": "KIMONDY:",
        "houseParty": "Domácí párty:",
        "meal": "Jídlo:",
        "party": "Vlevo, odjet:",
        "travel": "Cesta:",
        "university": "Univerzita",
        "studies": "Studie"
    },
    "activity": {
        "b2022_members": "členové včetně",
        "b2022_online": "online",
        "title": "Aktivita",
        "addressUnavailable": "Adresa je k dispozici pouze pro účastníky",
        "linkUnavailable": "Online odkaz je k dispozici pouze pro účastníky",
        "_2022e_swipeDownForMoreInfos": "Pro více informací přejděte dolů",
        "description": "Popis",
        "address": "Adresa",
        "chat": "Diskuse",
        "Vtype_message": "Klepněte na zprávu ...",
        "interessed": "Zájem",
        "followers": "Předplatitelé",
        "participants": "Účastníci",
        "invite": "Pozvat",
        "participate": "Účastnit se",
        "unsubscribe": "Odhlásit se",
        "about": "O události",
        "how": "Jak se najít",
        "translate": "přeložit",
        "language": "Vyberte jazyk",
        "readMore": "Přečtěte si více",
        "readLess": "Číst méně",
        "CopyPaste": "Zkopírujte a vložte a vytvořte si vlastní aktivitu",
        "help": "Pomoc a organizace",
        "edit": "Upravit",
        "delete": "VYMAZAT",
        "t2022Co_OrganiserWL": "Čekací listin spoluorganizátorů",
        "t2022_ChatSettings": "Parametry diskuse",
        "t2022_NotificationGroupChat": "Povolit oznámení v této diskusní skupině",
        "t2022_NotificationJoin": "Oznámení, když se osoba připojí ke skupině",
        "t2022_NotificationWithSound": "Oznámení se zvukem",
        "t2022_UnapprovedList": "Seznam lidí neschválených",
        "t2022_SeeAll": "Podívejte se na všechno",
        "t2022_WaitingList": "Pořadník",
        "t2022_Attendee_": "Účastník",
        "t2022_Information": "Organizátorovi této události můžete pomoci nebo vytvořit vlastní akci. Společně se socializujte!",
        "t2022_BuyTicket": "Koupit jízdenku",
        "t2022_Attendees": "Účastníci",
        "t2022_Age": "Stáří",
        "t2022_Pts": "Pts",
        "t2022_y-o": "roky",
        "t2022_contactOrga": "Kontaktujte náš tým Socializus na WhatsApp, abyste se stali organizátorem",
        "t2022_eventHost": "Hostitel události",
        "t2022_dialog_deleteConfirmation": "Jste si jistí, že to chcete smazat?",
        "t2022_dialog_yes": "Ano",
        "t2022_dialog_cancel": "zrušení",
        "t2022_dialog_cancelParticipationConfirmation": "Jste si jisti, že chcete svou účast zrušit?",
        "t2022_dialog_confirm": "Potvrdit",
        "t2022_dialog_adressOnlyForParticipants": "Jejda ! Adresa je k dispozici pouze pro účastníky",
        "t2022_dialog_participateNow": "Účastnit se",
        "t2022_dialog_otherPeopleComing": "Organizátoři vás informují",
        "t2022_dialog_gotIt": "Pochopeno",
        "t2022_dialog_repeatedActivityDialogText": "Tato událost se opakuje, chcete zrušit všechny dotyčné aktivity nebo pouze tyto?",
        "t2022_dialog_deleteOneActivity": "Smazat pouze tuto aktivitu",
        "t2022_dialog_deleteAllActivitiesOccurences": "Odstraňte všechny výskyty této činnosti",
        "t2022_dialog_confirmEmailInfo": "Pouze uživatelé, kteří ověřili svou e -mailovou adresu, jsou oprávněni vytvářet aktivitu",
        "t2022_dialog_confirmEmailInfo_check": "Zkontroluj můj e-mail"
    },
    "activities": {
        "afterwork": "Po práci",
        "apero": "Aperitiv",
        "business": "Podnikání",
        "culture": "Kultura",
        "dancing": "Tanec",
        "games": "Hry",
        "linguistic": "Lingvistické",
        "meal": "Jídlo",
        "movies": "Filmy",
        "music": "Hudba",
        "mutualHelp": "Vzájemná pomoc",
        "party": "Oslava",
        "picnic": "Piknik",
        "privateParty": "Soukromá party",
        "sport": "Sport",
        "travel": "Cesta"
    },
    "b2022_news": {
        "mainTitle": "Socializus je ...",
        "nonProfit": "Neziskové sdružení, které pomáhá mezinárodním sborům setkat, organizovat a sdílet akce.",
        "activeUsers": "27 000 aktivních uživatelů (a neustále rostoucí!) Netrpělivé diskusi a setkání",
        "freeApp": "Bezplatná aplikace, která vám pomůže socializovat a navázat nové přátele prostřednictvím bezplatných nebo placených aktivit",
        "helpTheApp": "K vylepšení aplikace potřebujeme vaši pomoc! Předejte slovo, přidejte přátele do naší skupiny FB nebo se staňte organizátorem.",
        "joinFB": "Připojte se ke skupině FB",
        "findEvent": "Najděte moji událost"
    },
    "friends": {
        "label": "[#1] Kontakty se zatím připojily k vašemu kruhu Socializus",
        "invite": "Pozvěte pomocí dalšího",
        "inviteEmail": "Pozvěte pomocí e -mailu",
        "inviteFacebook": "Pozvěte pomocí Facebooku",
        "inviteWhatsapp": "Pozvěte pomocí WhatsApp",
        "inviteTextMessage": "Pozvěte pomocí textové zprávy",
        "inviteTwitter": "Pozvěte pomocí Twitteru",
        "inviteInstagram": "Pozvěte pomocí Instagramu",
        "inviteTiktok": "Pozvěte pomocí Tiktoku",
        "inviteSnapchat": "Pozvěte pomocí Snapchat"
    },
    "filter": {
        "radius": "Aktivity kolem vás:",
        "select": "Vyberte téma:",
        "specifications": "Aktivity se specifikacemi:",
        "age": "Věk:",
        "past": "Minulé události",
        "next": "Následující události",
        "apply": "Naneste filtr"
    }
}